hpylib/__init__.py
hpylib-0.1.0.dist-info/licenses/LICENSE
hpylib-0.1.0.dist-info/METADATA
hpylib-0.1.0.dist-info/WHEEL
hpylib-0.1.0.dist-info/top_level.txt
hpylib-0.1.0.dist-info/RECORD
